phycus/__init__.py
phycus/api_client.py
phycus/configuration.py
phycus/rest.py
phycus/apis/__init__.py
phycus/apis/default_api.py
phycus/apis/population_api_api.py
phycus/models/__init__.py
phycus/models/access_data.py
phycus/models/cohort_data.py
phycus/models/error.py
phycus/models/frequency_error.py
phycus/models/genotype.py
phycus/models/genotype_list.py
phycus/models/genotype_method.py
phycus/models/haplotype_frequency.py
phycus/models/haplotype_frequency_data.py
phycus/models/hf_curation_list_response.py
phycus/models/hf_curation_request.py
phycus/models/hf_curation_response.py
phycus/models/label.py
phycus/models/label_data.py
phycus/models/label_list.py
phycus/models/license.py
phycus/models/method.py
phycus/models/method_data.py
phycus/models/method_list.py
phycus/models/population_data.py
phycus/models/population_request.py
phycus/models/population_response.py
phycus/models/population_submission_data.py
phycus/models/population_submission_response.py
phycus/models/quality.py
phycus/models/resolution_data.py
phycus/models/resolution_info.py
phycus/models/scope_data.py
phycus/models/scope_element.py
phycus-0.0.1.data/scripts/phycus-extract
phycus-0.0.1.data/scripts/phycus-import
phycus-0.0.1.dist-info/DESCRIPTION.rst
phycus-0.0.1.dist-info/METADATA
phycus-0.0.1.dist-info/RECORD
phycus-0.0.1.dist-info/WHEEL
phycus-0.0.1.dist-info/metadata.json
phycus-0.0.1.dist-info/top_level.txt
